{"columns": ["Company_ID", "Company_Name", "Email", "Phone", "Country", "Founded_Date", "Industry", "Status", "Employee_Count"], "rows": [{"Company_ID": 1, "Company_Name": "Oneal Inc", "Email": "mindyharrington@hansen.com", "Phone": "001-947-137-8407x122", "Country": "Grenada", "Founded_Date": "2017-09-28", "Industry": "Retail", "Status": "Pending", "Employee_Count": 3241}, {"Company_ID": 2, "Company_Name": "Sanchez, Bishop and Martin", "Email": "scottdiana@love.com", "Phone": "(411)066-2310x7950", "Country": "Equatorial Guinea", "Founded_Date": "2006-11-14", "Industry": "Healthcare", "Status": "Active", "Employee_Count": 5690}, {"Company_ID": 3, "Company_Name": "Merritt-King", "Email": "susan52@ryan.net", "Phone": "164.552.7254x821", "Country": "Argentina", "Founded_Date": "2013-04-02", "Industry": "Education", "Status": "Closed", "Employee_Count": 1340}, {"Company_ID": 4, "Company_Name": "Mcdonald-Huynh", "Email": "qaguilar@smith.com", "Phone": "(277)735-5042x52611", "Country": "Ghana", "Founded_Date": "1996-09-30", "Industry": "Technology", "Status": "Active", "Employee_Count": 6380}, {"Company_ID": 5, "Company_Name": "Russo Ltd", "Email": "martinbrandy@mitchell.com", "Phone": "(892)094-5719x075", "Country": "Denmark", "Founded_Date": "2020-08-22", "Industry": "Retail", "Status": "Closed", "Employee_Count": 5963}, {"Company_ID": 6, "Company_Name": "Wolf, Ortiz and Brooks", "Email": "ajenkins@norman.biz", "Phone": "7176668423", "Country": "Bangladesh", "Founded_Date": "2005-12-06", "Industry": "Healthcare", "Status": "Inactive", "Employee_Count": 4586}, {"Company_ID": 7, "Company_Name": "Arnold, Floyd and Hardy", "Email": "joseph51@daniels.com", "Phone": "+1-440-382-8955x12644", "Country": "Greece", "Founded_Date": "2007-01-26", "Industry": "Education", "Status": "Closed", "Employee_Count": 1486}, {"Company_ID": 8, "Company_Name": "Carr-Collins", "Email": "zacharyroberson@figueroa-yang.net", "Phone": "5478814726", "Country": "Liechtenstein", "Founded_Date": "2001-11-26", "Industry": "Manufacturing", "Status": "Inactive", "Employee_Count": 7929}, {"Company_ID": 9, "Company_Name": "Shaw-Scott", "Email": "fkramer@morris-graham.org", "Phone": "097-686-7579", "Country": "Marshall Islands", "Founded_Date": "2012-03-27", "Industry": "Education", "Status": "Active", "Employee_Count": 9594}, {"Company_ID": 10, "Company_Name": "Marshall-Fowler", "Email": "igeorge@randall.net", "Phone": "(261)929-9142x7373", "Country": "Tanzania", "Founded_Date": "2025-03-17", "Industry": "Education", "Status": "Pending", "Employee_Count": 7508}, {"Company_ID": 11, "Company_Name": "Bell Ltd", "Email": "rochamary@herrera-flores.com", "Phone": "6801722138", "Country": "Bermuda", "Founded_Date": "2016-05-10", "Industry": "Retail", "Status": "Closed", "Employee_Count": 8468}, {"Company_ID": 12, "Company_Name": "Ellis, Sullivan and Frank", "Email": "sally35@spencer.info", "Phone": "001-136-887-3661x5860", "Country": "Falkland Islands (Malvinas)", "Founded_Date": "1999-05-08", "Industry": "Manufacturing", "Status": "Inactive", "Employee_Count": 5978}, {"Company_ID": 13, "Company_Name": "Hernandez, Robles and Ball", "Email": "kimberlywarner@hernandez.org", "Phone": "(481)980-8526x759", "Country": "Guatemala", "Founded_Date": "1998-07-20", "Industry": "Manufacturing", "Status": "Inactive", "Employee_Count": 3651}, {"Company_ID": 14, "Company_Name": "Carpenter, Weaver and Gibson", "Email": "hodgeryan@wright.com", "Phone": "4528185839", "Country": "Croatia", "Founded_Date": "2002-08-20", "Industry": "Technology", "Status": "Inactive", "Employee_Count": 2113}, {"Company_ID": 15, "Company_Name": "Wilson-Quinn", "Email": "katrinajenkins@grant.biz", "Phone": "001-146-707-3174", "Country": "Saint Kitts and Nevis", "Founded_Date": "2022-02-15", "Industry": "Healthcare", "Status": "Inactive", "Employee_Count": 1991}, {"Company_ID": 16, "Company_Name": "Horton-Reid", "Email": "bradley48@santiago.com", "Phone": "001-367-123-8345x02654", "Country": "Honduras", "Founded_Date": "2015-03-23", "Industry": "Retail", "Status": "Pending", "Employee_Count": 3914}, {"Company_ID": 17, "Company_Name": "Smith, Whitaker and Murphy", "Email": "sean03@rodriguez.com", "Phone": "465.254.3354", "Country": "Lesotho", "Founded_Date": "2001-01-26", "Industry": "Healthcare", "Status": "Closed", "Employee_Count": 93}, {"Company_ID": 18, "Company_Name": "Ford and Sons", "Email": "valeriehansen@webb.info", "Phone": "+1-151-681-7039x363", "Country": "Zimbabwe", "Founded_Date": "2011-11-07", "Industry": "Retail", "Status": "Closed", "Employee_Count": 6464}, {"Company_ID": 19, "Company_Name": "Dillon-Cannon", "Email": "gmeyer@mckee.biz", "Phone": "+1-655-727-1173x91194", "Country": "Uruguay", "Founded_Date": "1996-04-04", "Industry": "Healthcare", "Status": "Closed", "Employee_Count": 2740}, {"Company_ID": 20, "Company_Name": "Huffman Inc", "Email": "clarkcrystal@white.com", "Phone": "001-103-900-4434x419", "Country": "Uzbekistan", "Founded_Date": "2014-08-13", "Industry": "Retail", "Status": "Inactive", "Employee_Count": 92}, {"Company_ID": 21, "Company_Name": "Lang Inc", "Email": "victor51@baker-schmidt.org", "Phone": "6577604931", "Country": "India", "Founded_Date": "2010-11-18", "Industry": "Finance", "Status": "Closed", "Employee_Count": 3463}, {"Company_ID": 22, "Company_Name": "Estes Inc", "Email": "shawnicholas@brown.org", "Phone": "001-635-021-2420x35773", "Country": "Christmas Island", "Founded_Date": "2009-05-17", "Industry": "Education", "Status": "Inactive", "Employee_Count": 6718}, {"Company_ID": 23, "Company_Name": "White-Roberts", "Email": "jdillon@benjamin.net", "Phone": "+1-231-325-7157x0572", "Country": "Zambia", "Founded_Date": "2015-05-03", "Industry": "Retail", "Status": "Active", "Employee_Count": 7250}, {"Company_ID": 24, "Company_Name": "Valdez, Erickson and Martinez", "Email": "sarahrogers@george.com", "Phone": "644.311.0544", "Country": "Morocco", "Founded_Date": "2008-03-19", "Industry": "Education", "Status": "Inactive", "Employee_Count": 1022}, {"Company_ID": 25, "Company_Name": "Rodriguez-Lucero", "Email": "michellehinton@davis-owens.biz", "Phone": "+1-667-066-0468x987", "Country": "Kyrgyz Republic", "Founded_Date": "1999-07-15", "Industry": "Manufacturing", "Status": "Active", "Employee_Count": 3427}, {"Company_ID": 26, "Company_Name": "Shannon-Fuller", "Email": "zhoward@walker-smith.com", "Phone": "+1-993-780-8817x58738", "Country": "Sierra Leone", "Founded_Date": "2012-10-02", "Industry": "Technology", "Status": "Pending", "Employee_Count": 501}, {"Company_ID": 27, "Company_Name": "Garrison and Sons", "Email": "kingbarbara@hansen-miller.com", "Phone": "831.662.7731", "Country": "Tuvalu", "Founded_Date": "2019-06-11", "Industry": "Finance", "Status": "Active", "Employee_Count": 2493}, {"Company_ID": 28, "Company_Name": "Andrews Group", "Email": "kendra67@santiago-rogers.info", "Phone": "105.013.3099x946", "Country": "India", "Founded_Date": "2025-01-16", "Industry": "Technology", "Status": "Inactive", "Employee_Count": 7008}, {"Company_ID": 29, "Company_Name": "Lopez-Moore", "Email": "cantrellmegan@curry-moore.com", "Phone": "809.570.9618x4391", "Country": "Azerbaijan", "Founded_Date": "2022-03-06", "Industry": "Education", "Status": "Closed", "Employee_Count": 1577}, {"Company_ID": 30, "Company_Name": "Buck-Lee", "Email": "kathryn52@fischer.com", "Phone": "(249)479-4588", "Country": "Holy See (Vatican City State)", "Founded_Date": "2013-11-17", "Industry": "Healthcare", "Status": "Inactive", "Employee_Count": 6754}, {"Company_ID": 31, "Company_Name": "Deleon, Lee and Beasley", "Email": "jennifer07@hernandez.org", "Phone": "(157)708-1110", "Country": "Sudan", "Founded_Date": "2015-03-01", "Industry": "Retail", "Status": "Inactive", "Employee_Count": 1139}, {"Company_ID": 32, "Company_Name": "Nunez-Woods", "Email": "bethany00@clark.com", "Phone": "001-608-089-6202x73018", "Country": "Guinea", "Founded_Date": "2023-10-28", "Industry": "Healthcare", "Status": "Pending", "Employee_Count": 904}, {"Company_ID": 33, "Company_Name": "Holmes PLC", "Email": "jasminehernandez@stephens-johnson.net", "Phone": "(761)095-4346x44603", "Country": "Kazakhstan", "Founded_Date": "2018-02-02", "Industry": "Education", "Status": "Inactive", "Employee_Count": 9488}, {"Company_ID": 34, "Company_Name": "Shaw, Moore and Nichols", "Email": "tracypowers@robinson-cantrell.com", "Phone": "+1-306-753-5965x922", "Country": "India", "Founded_Date": "2009-11-03", "Industry": "Technology", "Status": "Inactive", "Employee_Count": 9111}, {"Company_ID": 35, "Company_Name": "Reyes, Hardy and Smith", "Email": "michaeljones@hall.com", "Phone": "601.515.9597x639", "Country": "Russian Federation", "Founded_Date": "2002-05-04", "Industry": "Finance", "Status": "Closed", "Employee_Count": 3973}, {"Company_ID": 36, "Company_Name": "Fuller Ltd", "Email": "dianehendricks@hernandez.com", "Phone": "468.829.9065x9234", "Country": "Belize", "Founded_Date": "2005-06-01", "Industry": "Education", "Status": "Inactive", "Employee_Count": 4842}, {"Company_ID": 37, "Company_Name": "Clarke LLC", "Email": "barneswendy@carpenter-phillips.com", "Phone": "3525448565", "Country": "Malta", "Founded_Date": "2011-06-01", "Industry": "Education", "Status": "Inactive", "Employee_Count": 5385}, {"Company_ID": 38, "Company_Name": "Baker, Gould and Harper", "Email": "dmorgan@barnes.biz", "Phone": "7299276253", "Country": "Saint Pierre and Miquelon", "Founded_Date": "2004-06-16", "Industry": "Finance", "Status": "Inactive", "Employee_Count": 4653}, {"Company_ID": 39, "Company_Name": "Hahn and Sons", "Email": "frank98@fuller-dalton.info", "Phone": "(864)376-9072x477", "Country": "Namibia", "Founded_Date": "2015-02-05", "Industry": "Finance", "Status": "Closed", "Employee_Count": 7684}, {"Company_ID": 40, "Company_Name": "Archer Inc", "Email": "darren31@lopez.com", "Phone": "872-918-1433", "Country": "Tajikistan", "Founded_Date": "2000-09-11", "Industry": "Manufacturing", "Status": "Inactive", "Employee_Count": 953}, {"Company_ID": 41, "Company_Name": "Gordon, Mora and Perez", "Email": "jonathonhurst@sampson.com", "Phone": "(308)745-4923x0508", "Country": "Lao People's Democratic Republic", "Founded_Date": "2020-01-19", "Industry": "Retail", "Status": "Inactive", "Employee_Count": 2727}, {"Company_ID": 42, "Company_Name": "Wood, Atkins and Campbell", "Email": "manningsarah@juarez.com", "Phone": "376-690-9747x96733", "Country": "Colombia", "Founded_Date": "1998-05-16", "Industry": "Education", "Status": "Active", "Employee_Count": 516}, {"Company_ID": 43, "Company_Name": "Santos PLC", "Email": "charleskelly@smith.com", "Phone": "(472)805-2470", "Country": "Antarctica (the territory South of 60 deg S)", "Founded_Date": "2009-11-24", "Industry": "Manufacturing", "Status": "Inactive", "Employee_Count": 9144}, {"Company_ID": 44, "Company_Name": "Williams, Hill and Middleton", "Email": "whitedaniel@watson.net", "Phone": "7217558593", "Country": "Romania", "Founded_Date": "2008-12-13", "Industry": "Manufacturing", "Status": "Pending", "Employee_Count": 9163}, {"Company_ID": 45, "Company_Name": "Kennedy PLC", "Email": "rodriguezlauren@graham-brown.com", "Phone": "+1-196-381-5933x558", "Country": "Tuvalu", "Founded_Date": "2010-07-31", "Industry": "Finance", "Status": "Inactive", "Employee_Count": 9811}, {"Company_ID": 46, "Company_Name": "Davis-Archer", "Email": "matthew30@robinson.com", "Phone": "(133)081-4400x028", "Country": "Guinea", "Founded_Date": "2018-09-03", "Industry": "Healthcare", "Status": "Pending", "Employee_Count": 7543}, {"Company_ID": 47, "Company_Name": "Alvarado, Jacobs and Hess", "Email": "alexandra68@patel.com", "Phone": "411-159-9422", "Country": "France", "Founded_Date": "2016-11-06", "Industry": "Technology", "Status": "Active", "Employee_Count": 5289}, {"Company_ID": 48, "Company_Name": "Murray, Durham and Johnson", "Email": "matthew01@george.com", "Phone": "303-221-8388", "Country": "Burkina Faso", "Founded_Date": "1996-05-11", "Industry": "Finance", "Status": "Pending", "Employee_Count": 5321}, {"Company_ID": 49, "Company_Name": "Johnson-Thompson", "Email": "paul31@allen.com", "Phone": "+1-831-786-5988x815", "Country": "Puerto Rico", "Founded_Date": "2024-12-21", "Industry": "Manufacturing", "Status": "Pending", "Employee_Count": 2940}, {"Company_ID": 50, "Company_Name": "Miller PLC", "Email": "anthony00@deleon.com", "Phone": "969.070.1089x94946", "Country": "Germany", "Founded_Date": "1999-07-16", "Industry": "Healthcare", "Status": "Active", "Employee_Count": 3123}], "row_count": 50, "filename": "sample_company_data.csv"}